Dimension45/__init__.py
Dimension56-0.0.dist-info/METADATA
Dimension56-0.0.dist-info/WHEEL
Dimension56-0.0.dist-info/license
Dimension56-0.0.dist-info/top_level.txt
Dimension56-0.0.dist-info/RECORD
