Metadata-Version: 2.1
Name: Dimension56
Version: 0.0
Summary: Package for Dimension Reduction
Author: Hanzlah Shah
Author-email: shahhanzlah90@gmail.com
Classifier: Development Status :: 3 - Alpha
Classifier: Intended Audience :: Developers
Classifier: Topic :: Software Development :: Build Tools
Classifier: License :: OSI Approved :: MIT License
Requires-Python: >=3.6,<4.0
License-File: license
Requires-Dist: numpy
Requires-Dist: pandas
Requires-Dist: sklearn
